s3du/__init__.py
s3du/__main__.py
s3du/main.py
s3du-0.9.dist-info/LICENSE
s3du-0.9.dist-info/METADATA
s3du-0.9.dist-info/WHEEL
s3du-0.9.dist-info/entry_points.txt
s3du-0.9.dist-info/top_level.txt
s3du-0.9.dist-info/RECORD
