Metadata-Version: 2.1
Name: s3du
Version: 0.9
Summary: Inspect Amazon S3 buckets interactively with ncdu
Home-page: http://github.com/umonkey/s3du
Author: Justin Forest
Author-email: hex@umonkey.net
License: GNU GPL
Platform: UNKNOWN
Classifier: Development Status :: 4 - Beta
Classifier: Environment :: Console
Classifier: Intended Audience :: Developers
Classifier: Intended Audience :: System Administrators
Classifier: Operating System :: OS Independent
Classifier: Programming Language :: Python :: 2
Classifier: Programming Language :: Python :: 3
Classifier: Topic :: System :: Systems Administration
Classifier: Topic :: Utilities
License-File: LICENSE
Requires-Dist: boto3
